graphembedding/__init__.py
graphembedding/dataset.py
graphembedding/embedding.py
graphembedding/layers.py
graphembedding/models.py
graphembedding/playground/__init__.py
graphembedding/playground/github.py
graphembedding-0.1.dist-info/LICENSE
graphembedding-0.1.dist-info/METADATA
graphembedding-0.1.dist-info/WHEEL
graphembedding-0.1.dist-info/top_level.txt
graphembedding-0.1.dist-info/RECORD
