Metadata-Version: 2.1
Name: graphembedding
Version: 0.1
Summary: Python Graph Embedding Library for Knowledge graph
Home-page: https://github.com/vienna-project/graphembedding
Author: craftsangjae
Author-email: craftsangjae@gmail.com
License: MIT
Platform: UNKNOWN
Classifier: Programming Language :: Python :: 3
Requires-Python: >=3
Requires-Dist: pandas
Requires-Dist: tqdm
Requires-Dist: numpy
Requires-Dist: scikit-learn
Requires-Dist: tensorflow (>=2.2.0)
